{"@context":"https://schema.org","@type":"Event","name":"Digital Expresso #3 ; La cybersécurité, tous concernés: sécuriser mes données et mon entreprise","description":"\n      <p><strong>Digital Expresso #3 ; La cybersécurité, tous concernés: sécuriser mes données et mon entreprise</strong></p>\n<p>Ce Digital Expresso vous propose des solutions concrètes, adaptées aux petites structures, pour renforcer la sécurité de vos données sans mobiliser des ressources techniques ou financières démesurées.<br>Nous aborderons les risques spécifiques auxquels les petites entreprises sont exposées, les erreurs fréquentes à éviter, et les premières actions simples à mettre en place pour mieux vous protéger. Vous découvrirez comment identifier les données sensibles de votre structure, sécuriser vos équipements, sensibiliser vos équipes et choisir les bons outils de protection, sans complexité inutile.<br>À travers des exemples concrets et des outils accessibles, cet échange vous permettra de clarifier les enjeux de la cybersécurité et de repartir avec des actions directement applicables à votre quotidien professionnel.</p>\n<p>🎙️ Vous profiterez des conseils de Stéphane THOREL, co-fondateur de Cybil, qui vous partagera son expérience et ses astuces pour aider les petites entreprises à se défendre</p>\n<p>Un moment idéal pour :<br>✅&nbsp;Repartir mieux armé pour protéger votre activité.<br>✅ Échanger autour de vos expériences.<br>✅ Réseauter dans une ambiance conviviale.</p>\n<p>📅 Mardi 6 Mai 2025</p>\n<p>⏰ De 8h30 à 10h</p>\n<p>🏠 À Cobalt (5 rue Victor Hugo, 86000 Poitiers)</p>\n<p>😁 Gratuit, sur inscription juste ici :&nbsp;</p>\n<p><a href=\"https://forms.gle/EH1vBufAkU38ddt5A\" target=\"_blank\" rel=\"noopener noreferrer\">https://forms.gle/EH1vBufAkU38ddt5A</a></p>\n<p>Organisé en partenariat avec la <a href=\"https://www.poitiers.cci.fr/\" target=\"_blank\" rel=\"noopener noreferrer\">CCI de la Vienne</a>, <a href=\"https://www.grandpoitiers.fr/\">Grand Poitiers Communauté Urbaine</a> et <a href=\"https://www.reseaucom86.fr/\">RéseauCom86</a>.</p>\n<p>&nbsp;</p>\n    ","startDate":"2025-05-06T08:30:00","endDate":"","location":{"@type":"Place","name":"Cobalt","address":{"@type":"PostalAddress","addressLocality":"86000 Poitiers","streetAddress":"5 Rue Victor Hugo"}},"image":"","organizer":"SPN ; CCI Vienne ; Grand Poitiers","url":"https://www.cobaltpoitiers.fr/agenda_1550.html"}